deepllm/__init__.py
deepllm/api.py
deepllm/configurator.py
deepllm/embedders.py
deepllm/horn_prover.py
deepllm/interactors.py
deepllm/params.py
deepllm/prompters.py
deepllm/recursors.py
deepllm/refiners.py
deepllm/tools.py
deepllm/vis.py
deepllm/apps/README.md
deepllm/apps/app.py
deepllm/apps/app.sh
deepllm/apps/install.sh
deepllm/apps/rel_graph.html
deepllm/apps/requirements.txt
deepllm/demos/README.md
deepllm/demos/__init__.py
deepllm/demos/demo.py
deepllm/demos/install.sh
deepllm/demos/requirements.txt
deepllm/demos/viz.py
deepllm/demos/wikifetch.py
deepllm/local_llms/README.md
deepllm/local_llms/__init__.py
deepllm/local_llms/install.sh
deepllm/local_llms/local_runs.py
deepllm/local_llms/requirements.txt
deepllm/local_llms/server.sh
deepllm/local_llms/test_vicuna.py
deepllm/tests/README.md
deepllm/tests/__init__.py
deepllm/tests/test_all.py
deepllm/tests/test_api.py
deepllm/tests/test_configurator.py
deepllm/tests/test_embedders.py
deepllm/tests/test_horn_prover.py
deepllm/tests/test_interactors.py
deepllm/tests/test_params.py
deepllm/tests/test_recursors.py
deepllm/tests/test_refiners.py
deepllm-0.9.1.dist-info/LICENSE
deepllm-0.9.1.dist-info/METADATA
deepllm-0.9.1.dist-info/WHEEL
deepllm-0.9.1.dist-info/top_level.txt
deepllm-0.9.1.dist-info/RECORD
