Metadata-Version: 2.1
Name: deepllm
Version: 0.9.1
Summary: Deep, recursive, goal-driven LLM explorer
Home-page: https://github.com/ptarau/recursors.git
Author: Paul Tarau
Author-email: paul.tarau@gmail.com
License: GPL-3
License-File: LICENSE
Requires-Dist: numpy
Requires-Dist: scipy
Requires-Dist: scikit-learn
Requires-Dist: openai
Requires-Dist: tiktoken
Requires-Dist: pyvis
